calculatepy/__init__.py
calculatepy/add.py
calculatepy/divide.py
calculatepy/multiply.py
calculatepy/subtract.py
calculatepy/type_fallback.py
calculatepy-0.7.dist-info/LICENSE.txt
calculatepy-0.7.dist-info/METADATA
calculatepy-0.7.dist-info/WHEEL
calculatepy-0.7.dist-info/top_level.txt
calculatepy-0.7.dist-info/RECORD
