Metadata-Version: 2.1
Name: calculatepy
Version: 0.7
Summary: CalculatePy is the fundamental package for mathematical operations with Python
Author: Vijendra Kumar
Author-email: Vijendra Kumar <skvijay007@gmail.com>
Classifier: Programming Language :: Python :: 3
Classifier: License :: OSI Approved :: MIT License
Classifier: Operating System :: OS Independent
Requires-Python: >=3.8
License-File: LICENSE.txt
